autofillcvlac/__init__.py
autofillcvlac/core.py
autofillcvlac-0.1.22.dist-info/licenses/LICENSE
autofillcvlac-0.1.22.dist-info/METADATA
autofillcvlac-0.1.22.dist-info/WHEEL
autofillcvlac-0.1.22.dist-info/top_level.txt
autofillcvlac-0.1.22.dist-info/RECORD
