Metadata-Version: 2.4
Name: autofillcvlac
Version: 0.1.22
Summary: A Python package for processing research data and CVLaC information
Author: autofillcvlac contributors
License: MIT License
Project-URL: Homepage, https://github.com/restrepo/autofillcvlac
Project-URL: Bug Reports, https://github.com/restrepo/autofillcvlac/issues
Project-URL: Source, https://github.com/restrepo/autofillcvlac
Classifier: Development Status :: 3 - Alpha
Classifier: Intended Audience :: Science/Research
Classifier: Programming Language :: Python :: 3
Classifier: Programming Language :: Python :: 3.8
Classifier: Programming Language :: Python :: 3.9
Classifier: Programming Language :: Python :: 3.10
Classifier: Programming Language :: Python :: 3.11
Classifier: Programming Language :: Python :: 3.12
Requires-Python: >=3.8
License-File: LICENSE
Requires-Dist: requests>=2.25.0
Requires-Dist: pandas>=1.3.0
Requires-Dist: helium>=5.1.0
Dynamic: license-file
